{
  "name": "okta_password_accessed",
  "description": "A user revealed another user's stored application password (application.user_membership.show_password).",
  "source_detection": "rules/okta_rules/okta_password_accessed.py",
  "environment": "okta",
  "dataset": "okta",
  "validation": {
    "status": "dormant_degraded",
    "hits_90d": 0,
    "notes": "Zero application.user_membership.show_password events in 90d. DEGRADED: the Panther rule only fires when the actor is NOT among the target Users (i.e. accessed someone else's password), comparing actor.alternateId against target[].alternateId. Honeycomb does not ingest target[].alternateId, so the actor-vs-target comparison cannot be reproduced; this spec fires on the event itself and surfaces actor + target display names for the analyst to judge. Tighten upstream if the self-access case proves noisy."
  },
  "query_spec": {
    "time_range": "1h",
    "filters": [
      { "column": "okta.event.type", "op": "=", "value": "application.user_membership.show_password" }
    ],
    "breakdowns": ["okta.actor.email", "okta.target.0.displayName", "okta.target.1.displayName"],
    "calculations": [{ "op": "COUNT" }]
  }
}
